outlier_pypck/__init__.py
outlier_pypck/outlier.py
outlier_pypck-1.0.0.dist-info/LICENSE
outlier_pypck-1.0.0.dist-info/METADATA
outlier_pypck-1.0.0.dist-info/WHEEL
outlier_pypck-1.0.0.dist-info/top_level.txt
outlier_pypck-1.0.0.dist-info/RECORD
