Metadata-Version: 2.1
Name: outlier-pypck
Version: 1.0.0
Summary: Outlier removal package
Home-page: https://github.com/nishchaym/outlier_py
Author: Nishchay Mahajan
Author-email: nmahajan_be17@thapar.edu
License: UNKNOWN
Platform: UNKNOWN
Classifier: Programming Language :: Python :: 3
Classifier: License :: OSI Approved :: MIT License
Classifier: Operating System :: OS Independent
Requires-Python: >=3.6
